exc_analyzer/__init__.py
exc_analyzer/api.py
exc_analyzer/config.py
exc_analyzer/constants.py
exc_analyzer/errors.py
exc_analyzer/exc-analyzer.png
exc_analyzer/helpers.py
exc_analyzer/i18n.py
exc_analyzer/logging_utils.py
exc_analyzer/main.py
exc_analyzer/preferences.py
exc_analyzer/print_utils.py
exc_analyzer/commands/__init__.py
exc_analyzer/commands/actions_audit.py
exc_analyzer/commands/advanced_secrets.py
exc_analyzer/commands/analysis.py
exc_analyzer/commands/commit_anomaly.py
exc_analyzer/commands/content_audit.py
exc_analyzer/commands/contrib_impact.py
exc_analyzer/commands/dork_scan.py
exc_analyzer/commands/file_history.py
exc_analyzer/commands/key.py
exc_analyzer/commands/scan_secrets.py
exc_analyzer/commands/security_score.py
exc_analyzer/commands/user_a.py
exc_analyzer/commands/user_anomaly.py
exc_analyzer/locale/en/messages.json
exc_analyzer/locale/tr/messages.json
exc_analyzer-1.2.1.dist-info/licenses/LICENSE
exc_analyzer-1.2.1.dist-info/METADATA
exc_analyzer-1.2.1.dist-info/WHEEL
exc_analyzer-1.2.1.dist-info/entry_points.txt
exc_analyzer-1.2.1.dist-info/top_level.txt
exc_analyzer-1.2.1.dist-info/RECORD
