Metadata-Version: 2.4
Name: exc-analyzer
Version: 1.2.1
Summary: Powerful Python tool for in-depth GitHub analysis, designed for multiple platforms and still in development.
Author-email: EXC <exc-analyzer@outlook.com>, brgkdm <brgkdm@proton.me>
License: MIT
Keywords: github,security,audit,scanner,developer-tools,exc-analyzer
Classifier: Programming Language :: Python :: 3
Classifier: License :: OSI Approved :: MIT License
Classifier: Operating System :: OS Independent
Classifier: Topic :: Security
Classifier: Intended Audience :: Developers
Requires-Python: >=3.7
License-File: LICENSE
Requires-Dist: requests
Requires-Dist: toml
Requires-Dist: packaging
Requires-Dist: colorama
Requires-Dist: tabulate
Requires-Dist: importlib_resources
Requires-Dist: keyring
Provides-Extra: dev
Requires-Dist: pytest>=7.0; extra == "dev"
Requires-Dist: responses>=0.25; extra == "dev"
Dynamic: license-file
